pymedquery/__init__.py
pymedquery/config/__init__.py
pymedquery/config/config.py
pymedquery/config/exceptions.py
pymedquery/config/logger.py
pymedquery/config/logger_object.py
pymedquery/data/processed/images_uids.gz
pymedquery/data/processed/images_uids.pkl
pymedquery/data/sql/create.sql
pymedquery/data/sql/test.sql
pymedquery/docs/__init__.py
pymedquery/docs/coverage.svg
pymedquery/docs/proj_logging/.gitkeep
pymedquery/medqueryInit.sh
pymedquery/minio_data_handler.py
pymedquery/mqInit.py
pymedquery/pg_crud_handler.py
pymedquery/pymq.py
pymedquery/sql/default/__init__.py
pymedquery/sql/default/col_query.sql
pymedquery/sql/default/image_affine_default_query.sql
pymedquery/sql/default/image_default_query.sql
pymedquery/src/__init__.py
pymedquery/src/helpers.py
pymedquery/src/utils.py
pymedquery-2.17.1b0.dist-info/LICENSE.md
pymedquery-2.17.1b0.dist-info/METADATA
pymedquery-2.17.1b0.dist-info/WHEEL
pymedquery-2.17.1b0.dist-info/entry_points.txt
pymedquery-2.17.1b0.dist-info/RECORD
