Metadata-Version: 2.1
Name: pymedquery
Version: 2.17.1b0
Summary: This is a python client for the medical-database MedQuery
License: LICENSE.md
Author: Jon E Nesvold
Author-email: jon.nesvold@pm.me
Requires-Python: >=3.8,<4.0
Classifier: License :: Other/Proprietary License
Classifier: Programming Language :: Python :: 3
Classifier: Programming Language :: Python :: 3.8
Classifier: Programming Language :: Python :: 3.9
Classifier: Programming Language :: Python :: 3.10
Classifier: Programming Language :: Python :: 3.11
Requires-Dist: blosc (>=1.10.6,<2.0.0)
Requires-Dist: colorlog (>=6.7.0,<7.0.0)
Requires-Dist: minio (>=7.1.0,<8.0.0)
Requires-Dist: numpy (>=1.21.0,<2.0.0)
Requires-Dist: passlib (>=1.7.4,<2.0.0)
Requires-Dist: psycopg2-binary (>=2.9.1,<3.0.0)
Requires-Dist: python-dotenv (>=0.18.0,<0.19.0)
Requires-Dist: requests (>=2.28.2,<3.0.0)
Requires-Dist: toml (>=0.10.2,<0.11.0)
Requires-Dist: tqdm (>=4.61.2,<5.0.0)
